simplebot_dice.py
simplebot_dice-1.0.0.dist-info/LICENSE
simplebot_dice-1.0.0.dist-info/METADATA
simplebot_dice-1.0.0.dist-info/WHEEL
simplebot_dice-1.0.0.dist-info/entry_points.txt
simplebot_dice-1.0.0.dist-info/top_level.txt
simplebot_dice-1.0.0.dist-info/RECORD
